pypolyhedralcubature/__init__.py
pypolyhedralcubature/polyhedralcubature.py
pypolyhedralcubature-0.2.0.dist-info/METADATA
pypolyhedralcubature-0.2.0.dist-info/WHEEL
pypolyhedralcubature-0.2.0.dist-info/RECORD
