Metadata-Version: 2.1
Name: pypolyhedralcubature
Version: 0.2.0
Summary: Multiple integration on convex polytopes.
Home-page: https://github.com/stla/PyPolyhedralCubature
License: GPL-3.0-only
Keywords: integration,polyhedron,polytope
Author: Stéphane Laurent
Author-email: laurent_step@outlook.fr
Requires-Python: >=3.10,<3.13
Classifier: License :: OSI Approved :: GNU General Public License v3 (GPLv3)
Classifier: Programming Language :: Python :: 3
Classifier: Programming Language :: Python :: 3.10
Classifier: Programming Language :: Python :: 3.11
Classifier: Programming Language :: Python :: 3.12
Provides-Extra: docs
Requires-Dist: numpy (>=1.26.2,<2.0.0)
Requires-Dist: pycddlib (>=2.1.7,<3.0.0)
Requires-Dist: pysimplicialcubature (>=0.2.0,<0.3.0)
Requires-Dist: scipy (>=1.11.0,<2.0.0)
Requires-Dist: sphinx (>=7.2.0,<8.0.0) ; extra == "docs"
Requires-Dist: sphinx-rtd-theme (>=1.3.0,<2.0.0) ; extra == "docs"
Requires-Dist: sphinxcontrib-napoleon (>=0.7,<0.8) ; extra == "docs"
Requires-Dist: sphinxcontrib-restbuilder (>=0.3,<0.4) ; extra == "docs"
Requires-Dist: sympy (>=1.12,<2.0)
Project-URL: Documentation, https://pypolyhedralcubature.readthedocs.io/en/latest/
